napari_3d_ortho_viewer/__init__.py
napari_3d_ortho_viewer/_crop_dock_list_widget.py
napari_3d_ortho_viewer/_crop_dock_widget.py
napari_3d_ortho_viewer/_dock_widget.py
napari_3d_ortho_viewer/_version.py
napari_3d_ortho_viewer/napari.yaml
napari_3d_ortho_viewer/toggle_visibility.py
napari_3d_ortho_viewer/_tests/__init__.py
napari_3d_ortho_viewer/_tests/test_dock_widget.py
napari_3d_ortho_viewer/_tests/test_togglelayers.py
napari_3d_ortho_viewer-0.1.5.dist-info/LICENSE
napari_3d_ortho_viewer-0.1.5.dist-info/METADATA
napari_3d_ortho_viewer-0.1.5.dist-info/WHEEL
napari_3d_ortho_viewer-0.1.5.dist-info/entry_points.txt
napari_3d_ortho_viewer-0.1.5.dist-info/top_level.txt
napari_3d_ortho_viewer-0.1.5.dist-info/RECORD
