Metadata-Version: 2.1
Name: napari-3d-ortho-viewer
Version: 0.1.5
Summary: Napari 3D Ortho Viewer - an ortho viewer for napari for 3D images
Home-page: https://github.com/gatoniel/napari-3d-ortho-viewer
Author: Niklas Netter
Author-email: niknett@gmail.com
License: MIT
Project-URL: Bug Tracker, https://github.com/gatoniel/napari-3d-ortho-viewer/issues
Project-URL: Documentation, https://github.com/gatoniel/napari-3d-ortho-viewer#README.md
Project-URL: Source Code, https://github.com/gatoniel/napari-3d-ortho-viewer
Project-URL: User Support, https://github.com/gatoniel/napari-3d-ortho-viewer/issues
Classifier: Development Status :: 2 - Pre-Alpha
Classifier: Framework :: napari
Classifier: Intended Audience :: Developers
Classifier: License :: OSI Approved :: MIT License
Classifier: Operating System :: OS Independent
Classifier: Programming Language :: Python
Classifier: Programming Language :: Python :: 3
Classifier: Programming Language :: Python :: 3 :: Only
Classifier: Programming Language :: Python :: 3.8
Classifier: Programming Language :: Python :: 3.9
Classifier: Programming Language :: Python :: 3.10
Classifier: Topic :: Scientific/Engineering :: Image Processing
Requires-Python: >=3.8
License-File: LICENSE
Requires-Dist: numpy
Requires-Dist: magicgui
Requires-Dist: qtpy
Requires-Dist: scikit-image
Provides-Extra: testing
Requires-Dist: tox ; extra == 'testing'
Requires-Dist: pytest ; extra == 'testing'
Requires-Dist: pytest-cov ; extra == 'testing'
Requires-Dist: pytest-qt ; extra == 'testing'
Requires-Dist: napari ; extra == 'testing'
Requires-Dist: pyqt5 ; extra == 'testing'
